isocodes/__init__.py
isocodes/cli.py
isocodes/py.typed
isocodes/__pyinstaller/__init__.py
isocodes/__pyinstaller/hook-isocodes.py
isocodes/__pyinstaller/test_pyinstaller.py
isocodes/share/iso-codes/json/iso_15924.json
isocodes/share/iso-codes/json/iso_3166-1.json
isocodes/share/iso-codes/json/iso_3166-2.json
isocodes/share/iso-codes/json/iso_3166-3.json
isocodes/share/iso-codes/json/iso_4217.json
isocodes/share/iso-codes/json/iso_639-2.json
isocodes/share/iso-codes/json/iso_639-3.json
isocodes/share/iso-codes/json/iso_639-5.json
isocodes/share/locale/ab/LC_MESSAGES/iso_3166-1.mo
isocodes/share/locale/ab/LC_MESSAGES/iso_3166.mo
isocodes/share/locale/ab/LC_MESSAGES/iso_639-5.mo
isocodes/share/locale/ab/LC_MESSAGES/iso_639_5.mo
isocodes/share/locale/ace/LC_MESSAGES/iso_3166-1.mo
isocodes/share/locale/ace/LC_MESSAGES/iso_3166.mo
isocodes/share/locale/ach/LC_MESSAGES/iso_3166-1.mo
isocodes/share/locale/ach/LC_MESSAGES/iso_3166.mo
isocodes/share/locale/af/LC_MESSAGES/iso_3166-1.mo
isocodes/share/locale/af/LC_MESSAGES/iso_3166-3.mo
isocodes/share/locale/af/LC_MESSAGES/iso_3166.mo
isocodes/share/locale/af/LC_MESSAGES/iso_639-2.mo
isocodes/share/locale/af/LC_MESSAGES/iso_639-3.mo
isocodes/share/locale/af/LC_MESSAGES/iso_639.mo
isocodes/share/locale/af/LC_MESSAGES/iso_639_3.mo
isocodes/share/locale/ak/LC_MESSAGES/iso_3166-1.mo
isocodes/share/locale/ak/LC_MESSAGES/iso_3166.mo
isocodes/share/locale/am/LC_MESSAGES/iso_3166-1.mo
isocodes/share/locale/am/LC_MESSAGES/iso_3166-3.mo
isocodes/share/locale/am/LC_MESSAGES/iso_3166.mo
isocodes/share/locale/am/LC_MESSAGES/iso_639-2.mo
isocodes/share/locale/am/LC_MESSAGES/iso_639-3.mo
isocodes/share/locale/am/LC_MESSAGES/iso_639.mo
isocodes/share/locale/am/LC_MESSAGES/iso_639_3.mo
isocodes/share/locale/an/LC_MESSAGES/iso_3166-1.mo
isocodes/share/locale/an/LC_MESSAGES/iso_3166.mo
isocodes/share/locale/ar/LC_MESSAGES/iso_15924.mo
isocodes/share/locale/ar/LC_MESSAGES/iso_3166-1.mo
isocodes/share/locale/ar/LC_MESSAGES/iso_3166-3.mo
isocodes-2025.8.22.dist-info/licenses/LICENSE
isocodes-2025.8.22.dist-info/METADATA
isocodes-2025.8.22.dist-info/WHEEL
isocodes-2025.8.22.dist-info/entry_points.txt
isocodes-2025.8.22.dist-info/top_level.txt
isocodes-2025.8.22.dist-info/RECORD
