Metadata-Version: 2.4
Name: isocodes
Version: 2025.8.22
Summary: This project provides lists of various ISO standards (e.g. country, language, language scripts, and currency names) in one place
Author-email: Atem18 <contact@atemlire.com>
License:                   GNU LESSER GENERAL PUBLIC LICENSE
Project-URL: homepage, https://github.com/Atem18/isocodes
Project-URL: repository, https://github.com/Atem18/isocodes
Keywords: iso
Classifier: License :: OSI Approved :: MIT License
Classifier: Programming Language :: Python :: 3 :: Only
Classifier: Programming Language :: Python :: 3.9
Classifier: Programming Language :: Python :: 3.10
Classifier: Programming Language :: Python :: 3.11
Classifier: Programming Language :: Python :: 3.12
Classifier: Programming Language :: Python :: 3.13
Requires-Python: >=3.9
License-File: LICENSE
Dynamic: license-file
